autogluon.multimodal-1.4.0-py3.9-nspkg.pth
autogluon/multimodal/__init__.py
autogluon/multimodal/constants.py
autogluon/multimodal/predictor.py
autogluon/multimodal/version.py
autogluon/multimodal/cli/__init__.py
autogluon/multimodal/cli/prepare_detection_dataset.py
autogluon/multimodal/cli/voc2coco.py
autogluon/multimodal/configs/__init__.py
autogluon/multimodal/configs/data/default.yaml
autogluon/multimodal/configs/distiller/default.yaml
autogluon/multimodal/configs/env/default.yaml
autogluon/multimodal/configs/matcher/default.yaml
autogluon/multimodal/configs/model/default.yaml
autogluon/multimodal/configs/optim/default.yaml
autogluon/multimodal/configs/pretrain/__init__.py
autogluon/multimodal/configs/pretrain/detection/__init__.py
autogluon/multimodal/configs/pretrain/detection/coco_detection.py
autogluon/multimodal/configs/pretrain/detection/default_runtime.py
autogluon/multimodal/configs/pretrain/detection/schedule_1x.py
autogluon/multimodal/configs/pretrain/detection/dino/dino-4scale_r50_8xb2-12e_coco.py
autogluon/multimodal/configs/pretrain/detection/dino/dino-5scale_swin-l_8xb2-12e_coco.py
autogluon/multimodal/configs/pretrain/detection/dino/dino-5scale_swin-l_8xb2-36e_coco.py
autogluon/multimodal/configs/pretrain/detection/dino/dino_swinl_tta.py
autogluon/multimodal/configs/pretrain/detection/dino/dino_tta.py
autogluon/multimodal/configs/pretrain/detection/faster_rcnn/__init__.py
autogluon/multimodal/configs/pretrain/detection/faster_rcnn/faster_rcnn_r50_fpn.py
autogluon/multimodal/configs/pretrain/detection/voc/__init__.py
autogluon/multimodal/configs/pretrain/detection/voc/faster_rcnn_r50_fpn_1x_voc0712.py
autogluon/multimodal/configs/pretrain/detection/voc/voc0712.py
autogluon/multimodal/configs/pretrain/detection/yolox/__init__.py
autogluon/multimodal/configs/pretrain/detection/yolox/yolox_l_8xb8-300e_coco.py
autogluon/multimodal/configs/pretrain/detection/yolox/yolox_m_8xb8-300e_coco.py
autogluon.multimodal-1.4.0.dist-info/LICENSE
autogluon.multimodal-1.4.0.dist-info/METADATA
autogluon.multimodal-1.4.0.dist-info/NOTICE
autogluon.multimodal-1.4.0.dist-info/WHEEL
autogluon.multimodal-1.4.0.dist-info/namespace_packages.txt
autogluon.multimodal-1.4.0.dist-info/top_level.txt
autogluon.multimodal-1.4.0.dist-info/zip-safe
autogluon.multimodal-1.4.0.dist-info/RECORD
