Metadata-Version: 2.1
Name: autogluon.multimodal
Version: 1.4.0
Summary: Fast and Accurate ML in 3 Lines of Code
Home-page: https://github.com/autogluon/autogluon
Author: AutoGluon Community
License: Apache-2.0
Project-URL: Documentation, https://auto.gluon.ai
Project-URL: Bug Reports, https://github.com/autogluon/autogluon/issues
Project-URL: Source, https://github.com/autogluon/autogluon/
Project-URL: Contribute!, https://github.com/autogluon/autogluon/blob/master/CONTRIBUTING.md
Platform: UNKNOWN
Classifier: Development Status :: 5 - Production/Stable
Classifier: Intended Audience :: Education
Classifier: Intended Audience :: Developers
Classifier: Intended Audience :: Science/Research
Classifier: Intended Audience :: Customer Service
Classifier: Intended Audience :: Financial and Insurance Industry
Classifier: Intended Audience :: Healthcare Industry
Classifier: Intended Audience :: Telecommunications Industry
Classifier: License :: OSI Approved :: Apache Software License
Classifier: Operating System :: MacOS
Classifier: Operating System :: Microsoft :: Windows
Classifier: Operating System :: POSIX
Classifier: Operating System :: Unix
Classifier: Programming Language :: Python :: 3
Classifier: Programming Language :: Python :: 3.9
Classifier: Programming Language :: Python :: 3.10
Classifier: Programming Language :: Python :: 3.11
Classifier: Programming Language :: Python :: 3.12
Classifier: Topic :: Software Development
Classifier: Topic :: Scientific/Engineering :: Artificial Intelligence
Classifier: Topic :: Scientific/Engineering :: Information Analysis
Classifier: Topic :: Scientific/Engineering :: Image Recognition
Requires-Python: >=3.9, <3.13
License-File: ../LICENSE
License-File: ../NOTICE
Requires-Dist: numpy<2.4.0,>=1.25.0
Requires-Dist: scipy<1.17,>=1.5.4
Requires-Dist: pandas<2.4.0,>=2.0.0
Requires-Dist: scikit-learn<1.8.0,>=1.4.0
Requires-Dist: Pillow<12,>=10.0.1
Requires-Dist: tqdm<5,>=4.38
Requires-Dist: boto3<2,>=1.10
Requires-Dist: torch<2.8,>=2.2
Requires-Dist: lightning<2.8,>=2.2
Requires-Dist: transformers[sentencepiece]<4.50,>=4.38.0
Requires-Dist: accelerate<2.0,>=0.34.0
Requires-Dist: fsspec[http]<=2025.3
Requires-Dist: requests<3,>=2.30
Requires-Dist: jsonschema<4.24,>=4.18
Requires-Dist: seqeval<1.3.0,>=1.2.2
Requires-Dist: evaluate<0.5.0,>=0.4.0
Requires-Dist: timm<1.0.7,>=0.9.5
Requires-Dist: torchvision<0.23.0,>=0.16.0
Requires-Dist: scikit-image<0.26.0,>=0.19.1
Requires-Dist: text-unidecode<1.4,>=1.3
Requires-Dist: torchmetrics<1.8,>=1.2.0
Requires-Dist: omegaconf<2.4.0,>=2.1.1
Requires-Dist: autogluon.core[raytune]==1.4.0
Requires-Dist: autogluon.features==1.4.0
Requires-Dist: autogluon.common==1.4.0
Requires-Dist: pytorch-metric-learning<2.9,>=1.3.0
Requires-Dist: nlpaug<1.2.0,>=1.1.10
Requires-Dist: nltk<3.10,>=3.4.5
Requires-Dist: openmim<0.4.0,>=0.3.7
Requires-Dist: defusedxml<0.7.2,>=0.7.1
Requires-Dist: jinja2<3.2,>=3.0.3
Requires-Dist: tensorboard<3,>=2.9
Requires-Dist: pytesseract<0.4,>=0.3.9
Requires-Dist: nvidia-ml-py3<8.0,>=7.352.0
Requires-Dist: pdf2image<1.19,>=1.17.0
Provides-Extra: tests
Requires-Dist: ruff; extra == "tests"
Requires-Dist: datasets<3.6.0,>=2.16.0; extra == "tests"
Requires-Dist: onnxruntime<1.22.0,>=1.17.0; extra == "tests"
Requires-Dist: onnxruntime-gpu<1.22.0,>=1.17.0; (platform_system != "Darwin" and platform_machine != "aarch64") and extra == "tests"
Requires-Dist: onnx<1.18.0,>=1.13.0; platform_system != "Windows" and extra == "tests"
Requires-Dist: tensorrt<10.9.1,>=8.6.0; (platform_system == "Linux" and python_version < "3.11") and extra == "tests"
Requires-Dist: onnx<1.16.2,>=1.13.0; platform_system == "Windows" and extra == "tests"
